[
  {
    "_id": "drako",
    "nom": "Drako",
    "espece_nom": "kangourou",
    "naissance": "",
    "deces": "",
    "sexe": "M",
    "observations": "",
    "position": "dedans"
  },
  {
    "_id": "ginger",
    "nom": "Ginger",
    "espece_nom": "kangourou",
    "naissance": "",
    "deces": "",
    "sexe": "F",
    "observations": "",
    "position": "dedans"
  },
  {
    "_id": "eucalyptus",
    "nom": "Eucalyptus",
    "espece_nom": "koala",
    "naissance": "",
    "deces": "",
    "sexe": "M",
    "observations": "",
    "position": "dedans"
  },
  {
    "_id": "peluche",
    "nom": "Peluche",
    "espece_nom": "koala",
    "naissance": "",
    "deces": "",
    "sexe": "F",
    "observations": "",
    "position": "dedans"
  },
  {
    "_id": "bolt",
    "nom": "Bolt",
    "espece_nom": "autruche",
    "naissance": "",
    "deces": "",
    "sexe": "M",
    "observations": "",
    "position": "dedans"
  },
  {
    "_id": "kalia",
    "nom": "Kalia",
    "espece_nom": "autruche",
    "naissance": "",
    "deces": "",
    "sexe": "F",
    "observations": "",
    "position": "dedans"
  },
  {
    "_id": "donatello",
    "nom": "Donatello",
    "espece_nom": "tortue",
    "naissance": "",
    "deces": "",
    "sexe": "M",
    "observations": "",
    "position": "dedans"
  },
  {
    "_id": "Raphaela",
    "nom": "Raphaela",
    "espece_nom": "tortue",
    "naissance": "",
    "deces": "",
    "sexe": "F",
    "observations": "",
    "position": "dedans"
  },
  {
    "_id": "bambou",
    "nom": "Bambou",
    "espece_nom": "panda",
    "naissance": "",
    "deces": "",
    "sexe": "M",
    "observations": "",
    "position": "dedans"
  },
  {
    "_id": "hao",
    "nom": "Hao",
    "espece_nom": "panda",
    "naissance": "",
    "deces": "",
    "sexe": "F",
    "observations": "",
    "position": "dedans"
  },
  {
    "_id": "shere-khan",
    "nom": "Shere Khan",
    "espece_nom": "tigre",
    "naissance": "",
    "deces": "",
    "sexe": "M",
    "observations": "",
    "position": "dedans"
  },
  {
    "_id": "hosuni",
    "nom": "Hosuni",
    "espece_nom": "tigre",
    "naissance": "",
    "deces": "",
    "sexe": "F",
    "observations": "",
    "position": "dedans"
  },
  {
    "_id": "pongo",
    "nom": "Pongo",
    "espece_nom": "orang-outan",
    "naissance": "",
    "deces": "",
    "sexe": "M",
    "observations": "",
    "position": "dedans"
  },
  {
    "_id": "sumtra",
    "nom": "Sumatra",
    "espece_nom": "orang-outan",
    "naissance": "",
    "deces": "",
    "sexe": "F",
    "observations": "",
    "position": "dedans"
  },
  {
    "_id": "aleksei",
    "nom": "Aleksei",
    "espece_nom": "rhinoceros",
    "naissance": "",
    "deces": "",
    "sexe": "M",
    "observations": "",
    "position": "dedans"
  },
  {
    "_id": "machu",
    "nom": "Machu",
    "espece_nom": "lama",
    "naissance": "",
    "deces": "",
    "sexe": "M",
    "observations": "",
    "position": "dedans"
  },
  {
    "_id": "enola",
    "nom": "Enola",
    "espece_nom": "lama",
    "naissance": "",
    "deces": "",
    "sexe": "F",
    "observations": "",
    "position": "dedans"
  },
  {
    "_id": "gala",
    "nom": "Gala",
    "espece_nom": "iguane",
    "naissance": "",
    "deces": "",
    "sexe": "F",
    "observations": "",
    "position": "dedans"
  },
  {
    "_id": "kaa",
    "nom": "Kaa",
    "espece_nom": "boa",
    "naissance": "",
    "deces": "",
    "sexe": "M",
    "observations": "",
    "position": "dedans"
  },
  {
    "_id": "blu",
    "nom": "Blu",
    "espece_nom": "ara",
    "naissance": "",
    "deces": "",
    "sexe": "M",
    "observations": "",
    "position": "dedans"
  },
  {
    "_id": "perla",
    "nom": "Perla",
    "espece_nom": "ara",
    "naissance": "",
    "deces": "",
    "sexe": "F",
    "observations": "",
    "position": "dedans"
  },
  {
    "_id": "kamel",
    "nom": "Kamel",
    "espece_nom": "chameau",
    "naissance": "",
    "deces": "",
    "sexe": "M",
    "observations": "",
    "position": "dedans"
  },
  {
    "_id": "finnick",
    "nom": "Finnick",
    "espece_nom": "fennec",
    "naissance": "",
    "deces": "",
    "sexe": "M",
    "observations": "",
    "position": "dedans"
  },
  {
    "_id": "popi",
    "nom": "Popi",
    "espece_nom": "fennec",
    "naissance": "",
    "deces": "",
    "sexe": "F",
    "observations": "",
    "position": "dedans"
  },
  {
    "_id": "salazar",
    "nom": "Salazar",
    "espece_nom": "vipere",
    "naissance": "",
    "deces": "",
    "sexe": "M",
    "observations": "",
    "position": "dedans"
  },
  {
    "_id": "iyotake",
    "nom": "Iyotake",
    "espece_nom": "bison",
    "naissance": "",
    "deces": "",
    "sexe": "M",
    "observations": "",
    "position": "dedans"
  },
  {
    "_id": "tatanka",
    "nom": "Tatanka",
    "espece_nom": "bison",
    "naissance": "",
    "deces": "",
    "sexe": "F",
    "observations": "",
    "position": "dedans"
  },
  {
    "_id": "yotanka",
    "nom": "Yotanka",
    "espece_nom": "bison",
    "naissance": "",
    "deces": "",
    "sexe": "F",
    "observations": "",
    "position": "dedans"
  },
  {
    "_id": "kodiak",
    "nom": "Kodiak",
    "espece_nom": "ours-noir",
    "naissance": "",
    "deces": "",
    "sexe": "M",
    "observations": "",
    "position": "dedans"
  },
  {
    "_id": "montana",
    "nom": "Montana",
    "espece_nom": "ours-noir",
    "naissance": "",
    "deces": "",
    "sexe": "F",
    "observations": "",
    "position": "dedans"
  },
  {
    "_id": "ulf",
    "nom": "Ulf",
    "espece_nom": "loup",
    "naissance": "",
    "deces": "",
    "sexe": "M",
    "observations": "mâle alpha",
    "position": "dedans"
  },
  {
    "_id": "uma",
    "nom": "Uma",
    "espece_nom": "loup",
    "naissance": "",
    "deces": "",
    "sexe": "F",
    "observations": "femelle alpha",
    "position": "dedans"
  },
  {
    "_id": "alaska",
    "nom": "Alaska",
    "espece_nom": "loup",
    "naissance": "",
    "deces": "",
    "sexe": "M",
    "observations": "mâle bêta",
    "position": "dedans"
  },
  {
    "_id": "ryley",
    "nom": "Ryley",
    "espece_nom": "loup",
    "naissance": "",
    "deces": "",
    "sexe": "F",
    "observations": "femelle bêta",
    "position": "dedans"
  },
  {
    "_id": "onyx",
    "nom": "Onyx",
    "espece_nom": "loup",
    "naissance": "",
    "deces": "",
    "sexe": "M",
    "observations": "",
    "position": "dedans"
  },
  {
    "_id": "iowa",
    "nom": "Iowa",
    "espece_nom": "aigle",
    "naissance": "",
    "deces": "",
    "sexe": "M",
    "observations": "",
    "position": "dedans"
  },
  {
    "_id": "sakari",
    "nom": "Sakari",
    "espece_nom": "ours-polaire",
    "naissance": "",
    "deces": "",
    "sexe": "F",
    "observations": "",
    "position": "dedans"
  },
  {
    "_id": "willy",
    "nom": "Willy",
    "espece_nom": "manchot",
    "naissance": "",
    "deces": "",
    "sexe": "M",
    "observations": "",
    "position": "dedans"
  },
  {
    "_id": "tuxa",
    "nom": "Tuxa",
    "espece_nom": "manchot",
    "naissance": "",
    "deces": "",
    "sexe": "F",
    "observations": "",
    "position": "dedans"
  },
  {
    "_id": "jasper",
    "nom": "Jasper",
    "espece_nom": "manchot",
    "naissance": "",
    "deces": "",
    "sexe": "M",
    "observations": "",
    "position": "dedans"
  },
  {
    "_id": "gorfa",
    "nom": "Gorfa",
    "espece_nom": "manchot",
    "naissance": "",
    "deces": "",
    "sexe": "F",
    "observations": "",
    "position": "dedans"
  },
  {
    "_id": "kourkova",
    "nom": "Kourkova",
    "espece_nom": "manchot",
    "naissance": "",
    "deces": "",
    "sexe": "F",
    "observations": "",
    "position": "dedans"
  },
  {
    "_id": "bibi",
    "nom": "Bibi",
    "espece_nom": "phoque",
    "naissance": "",
    "deces": "",
    "sexe": "M",
    "observations": "",
    "position": "dedans"
  },
  {
    "_id": "ouate",
    "nom": "Ouate",
    "espece_nom": "phoque",
    "naissance": "",
    "deces": "",
    "sexe": "F",
    "observations": "",
    "position": "dedans"
  },
  {
    "_id": "raphael",
    "nom": "Raphaël",
    "espece_nom": "suricate",
    "naissance": "",
    "deces": "",
    "sexe": "M",
    "observations": "",
    "position": "dedans"
  },
  {
    "_id": "justine",
    "nom": "Justine",
    "espece_nom": "suricate",
    "naissance": "",
    "deces": "",
    "sexe": "F",
    "observations": "",
    "position": "dedans"
  },
  {
    "_id": "julien",
    "nom": "Julien",
    "espece_nom": "suricate",
    "naissance": "",
    "deces": "",
    "sexe": "M",
    "observations": "",
    "position": "dedans"
  },
  {
    "_id": "lea",
    "nom": "Léa",
    "espece_nom": "suricate",
    "naissance": "",
    "deces": "",
    "sexe": "F",
    "observations": "",
    "position": "dedans"
  },
  {
    "_id": "vincent",
    "nom": "Vincent",
    "espece_nom": "suricate",
    "naissance": "",
    "deces": "",
    "sexe": "M",
    "observations": "",
    "position": "dedans"
  },
  {
    "_id": "eleonore",
    "nom": "Eléonore",
    "espece_nom": "suricate",
    "naissance": "",
    "deces": "",
    "sexe": "F",
    "observations": "",
    "position": "dedans"
  },
  {
    "_id": "tanza",
    "nom": "Tanza",
    "espece_nom": "gnou",
    "naissance": "",
    "deces": "",
    "sexe": "F",
    "observations": "",
    "position": "dedans"
  },
  {
    "_id": "namie",
    "nom": "Namie",
    "espece_nom": "gnou",
    "naissance": "",
    "deces": "",
    "sexe": "F",
    "observations": "",
    "position": "dedans"
  },
  {
    "_id": "hathi",
    "nom": "Hathi",
    "espece_nom": "elephant",
    "naissance": "",
    "deces": "",
    "sexe": "M",
    "observations": "",
    "position": "dedans"
  },
  {
    "_id": "jad-bal-ja",
    "nom": "Jad-bal-ja",
    "espece_nom": "lion",
    "naissance": "",
    "deces": "",
    "sexe": "M",
    "observations": "",
    "position": "dedans"
  },
  {
    "_id": "nala",
    "nom": "Nala",
    "espece_nom": "lion",
    "naissance": "",
    "deces": "",
    "sexe": "F",
    "observations": "",
    "position": "dedans"
  },
  {
    "_id": "enak",
    "nom": "Enak",
    "espece_nom": "girafe",
    "naissance": "",
    "deces": "",
    "sexe": "M",
    "observations": "",
    "position": "dedans"
  },
  {
    "_id": "kunta",
    "nom": "Kunta",
    "espece_nom": "girafe",
    "naissance": "",
    "deces": "",
    "sexe": "M",
    "observations": "",
    "position": "dedans"
  },
  {
    "_id": "marty",
    "nom": "Marty",
    "espece_nom": "zebre",
    "naissance": "",
    "deces": "",
    "sexe": "M",
    "observations": "",
    "position": "dedans"
  },
  {
    "_id": "siofa",
    "nom": "Siofa",
    "espece_nom": "zebre",
    "naissance": "",
    "deces": "",
    "sexe": "F",
    "observations": "",
    "position": "dedans"
  },
  {
    "_id": "ziggy",
    "nom": "Ziggy",
    "espece_nom": "vautour",
    "naissance": "",
    "deces": "",
    "sexe": "M",
    "observations": "",
    "position": "dedans"
  },
  {
    "_id": "buzzie",
    "nom": "Buzzie",
    "espece_nom": "vautour",
    "naissance": "",
    "deces": "",
    "sexe": "F",
    "observations": "",
    "position": "dedans"
  },
  {
    "_id": "dizzie",
    "nom": "Dizzie",
    "espece_nom": "vautour",
    "naissance": "",
    "deces": "",
    "sexe": "F",
    "observations": "",
    "position": "dedans"
  },
  {
    "_id": "yael",
    "nom": "Yaël",
    "espece_nom": "chamois",
    "naissance": "",
    "deces": "",
    "sexe": "M",
    "observations": "",
    "position": "dedans"
  },
  {
    "_id": "isabelle",
    "nom": "Isabelle",
    "espece_nom": "chamois",
    "naissance": "",
    "deces": "",
    "sexe": "F",
    "observations": "",
    "position": "dedans"
  },
  {
    "_id": "messidor",
    "nom": "Messidor",
    "espece_nom": "chamois",
    "naissance": "",
    "deces": "",
    "sexe": "M",
    "observations": "",
    "position": "dedans"
  },
  {
    "_id": "julie",
    "nom": "Julie",
    "espece_nom": "chamois",
    "naissance": "",
    "deces": "",
    "sexe": "F",
    "observations": "",
    "position": "dedans"
  },
  {
    "_id": "borealis",
    "nom": "Borealis",
    "espece_nom": "lynx",
    "naissance": "",
    "deces": "",
    "sexe": "F",
    "observations": "",
    "position": "dedans"
  },
  {
    "_id": "mudge",
    "nom": "Mudge",
    "espece_nom": "loutre",
    "naissance": "",
    "deces": "",
    "sexe": "M",
    "observations": "",
    "position": "dedans"
  },
  {
    "_id": "rappy",
    "nom": "Rappy",
    "espece_nom": "loutre",
    "naissance": "",
    "deces": "",
    "sexe": "F",
    "observations": "",
    "position": "dedans"
  },
  {
    "_id": "bobak",
    "nom": "Bobak",
    "espece_nom_nom": "marmotte",
    "naissance": "",
    "deces": "",
    "sexe": "M",
    "observations": "",
    "position": "dedans"
  },
  {
    "_id": "monax",
    "nom": "Monax",
    "espece_nom_nom": "marmotte",
    "naissance": "",
    "deces": "",
    "sexe": "F",
    "observations": "",
    "position": "dedans"
  },
  {
    "_id": "olympus",
    "nom": "Olympus",
    "espece_nom_nom": "marmotte",
    "naissance": "",
    "deces": "",
    "sexe": "M",
    "observations": "",
    "position": "dedans"
  },
  {
    "_id": "kamtchaka",
    "nom": "Kamtchaka",
    "espece_nom_nom": "marmotte",
    "naissance": "",
    "deces": "",
    "sexe": "M",
    "observations": "",
    "position": "dedans"
  },
  {
    "_id": "sibiraca",
    "nom": "Sibiraca",
    "espece_nom_nom": "marmotte",
    "naissance": "",
    "deces": "",
    "sexe": "F",
    "observations": "",
    "position": "dedans"
  },
  {
    "_id": "harry",
    "nom": "Harry",
    "espece_nom_nom": "chouette",
    "naissance": "",
    "deces": "",
    "sexe": "M",
    "observations": "",
    "position": "dedans"
  }
]